{"id":1,"userId":1,"originalName":"CV.pdf","rawText":"\n695 918 954\n\nKevin Molina\nDESARROLLADOR BACKEND JAVA | MICROSERVICIOS |\n\nSPRING BOOT | AGILE | APX (EN FORMACIÓN)\n\nKevin2001molina@gmail.com\n\nExperiencia\nDESARROLLADOR\nFUL-STACK \nALEBAT MANAGEMENT AND\nCONSULTING\n\nEUROFIRMS\n\nCOMERCIAL JEFE\nDE EQUIPO\n\nLiderazgo y desarrollo de equipos\nGestión de proyectos y objetivos\nComunicación efectiva con clientes\n\nTrabajo en proyectos ágiles\nPruebas unitarias y control de\ncalidad\nGestión de versiones con Git \nCoordinación de equipos\nDesarrollo con arquitecturas\nmodernas\n\nFormación\nGrado Superior en Desarrollo de\nAplicaciones Multiplataforma\n\nBachillerato Social\n\nIes María de Zayas y Sotomayor\n\nIes Margarita Salas\n\nIdiomas\n\nConocimientos digitales\n\nSobre mí\n\nHabilidades personales\n\nSpring Boot\nJava 17\nHibernate\nJUnit\nAPIs REST\nMaven\n\nMe considero una persona empática, dispuesto a ayudar y construir un buen\nambiente de trabajo. Me gusta mantenerme ocupado y siempre estoy buscando\naprender algo nuevo para seguir mejorando tanto profesional como\npersonalmente.\n\nInglés: Intermedio (en mejora continua)\n\nFrancés: Básico\n\nResolución de problemas\nGestión de equipos de trabajo\nOrganización y multitarea\nProactividad y aprendizaje\nconstante\nAdaptabilidad\nComunicación y empatía\n\nMicroservicios\nGit\nVue\nDocker\nStrapi\nAndroid\n\nCertificaciones\nFundamentos de IA generativa con\nPartyRock (Amazon Bedrock)\n\nhttps://github.com/Kevin2001mol\n\nDiseño de interfaces gráficas\n(GUI)\nTesting y depuración de código\nProgramación orientada a\nobjetos (POO)\nBases de datos relacionales\nModelado UML\n\nInquietudes\nBusco formar parte de un equipo que desarrolle soluciones Java modernas,\nusando microservicios, metodologías ágiles y tecnologías emergentes como\nAPX. Me interesa la mejora continua y la calidad del software.\n\nHabilidades técnicas\n\nAngular\nJDBC\nXML\nPython\nStrapi\nSQL\n\nProyectos personales\nCarreraPro – Asistente inteligente de reclutamiento (en desarrollo)\n\nBackend con Java 17 y Spring Boot, usando arquitectura en capas.\nProyecto en evolución, enfocado a microservicios y preparado para CI/CD.\nAPI REST con validaciones, control de errores y estructura modular.\nGestión de base de datos con PostgreSQL y JPA (Hibernate).\nControl de versiones con Git y uso de SonarLint para calidad del código.\n\n\n","createdAt":"2025-06-27T06:18:53.335677Z"}